core/__init__.py
core/constants/__init__.py
core/constants/bio_prompt.j2
core/constants/hard_merge_config.json
core/constants/log_emoji.json
core/constants/merge_table_llm.j2
core/constants/table_prompt.j2
core/constants/__pycache__/__init__.cpython-312.pyc
core/pipelines/README.md
core/pipelines/__init__.py
core/pipelines/bpai.py
core/pipelines/parse_form.py
core/pipelines/parse_table.py
core/pipelines/__pycache__/__init__.cpython-312.pyc
core/pipelines/__pycache__/base_renderer.cpython-312.pyc
core/pipelines/__pycache__/bpai.cpython-312.pyc
core/pipelines/__pycache__/doc_processing_pipeline.cpython-312.pyc
core/pipelines/__pycache__/doc_processing_pipeling.cpython-312.pyc
core/pipelines/__pycache__/json_renderer.cpython-312.pyc
core/pipelines/__pycache__/parse_form.cpython-312.pyc
core/pipelines/__pycache__/parse_table.cpython-312.pyc
core/pipelines/__pycache__/serializers.cpython-312.pyc
core/pipelines/utils/assign_config.py
core/pipelines/utils/utils.py
core/pipelines/utils/__pycache__/assign_config.cpython-312.pyc
core/pipelines/utils/__pycache__/utils.cpython-312.pyc
core/renderers/__init__.py
core/renderers/json_renderer.py
core/renderers/serializers.py
core/renderers/__pycache__/__init__.cpython-312.pyc
core/renderers/__pycache__/json_renderer.cpython-312.pyc
core/renderers/__pycache__/serializers.cpython-312.pyc
core/schemas/README.md
core/schemas/base_types.py
core/schemas/__pycache__/base_types.cpython-312.pyc
core/schemas/document/README.md
core/schemas/document/__init__.py
core/schemas/document/document.py
core/schemas/document/document.schema.json
core/schemas/document/math_utils.py
core/schemas/document/polygon.py
core/schemas/document/registry.py
core/schemas/document/settings.py
core/schemas/document/util.py
core/schemas/document/__pycache__/__init__.cpython-312.pyc
core/schemas/document/__pycache__/document.cpython-312.pyc
core/schemas/document/__pycache__/math_utils.cpython-312.pyc
core/schemas/document/__pycache__/polygon.cpython-312.pyc
test_saral_auto-0.1.0.dist-info/METADATA
test_saral_auto-0.1.0.dist-info/WHEEL
test_saral_auto-0.1.0.dist-info/entry_points.txt
test_saral_auto-0.1.0.dist-info/top_level.txt
test_saral_auto-0.1.0.dist-info/RECORD
