Metadata-Version: 2.4
Name: test-saral-auto
Version: 0.1.0
Summary: A system for processing documents to detect their type, extract fields, and generate templates
Author-email: Uncanny_70 <uncannydevs@gmail.com>
License: MIT
Project-URL: Homepage, https://github.com/Debatreya/saral-auto
Project-URL: Bug Tracker, https://github.com/Debatreya/saral-auto/issues
Classifier: Programming Language :: Python :: 3
Classifier: License :: OSI Approved :: MIT License
Classifier: Operating System :: OS Independent
Requires-Python: >=3.8
Requires-Dist: marker-pdf
Requires-Dist: pydantic
Requires-Dist: opencv-python
Requires-Dist: numpy
Requires-Dist: pillow
Requires-Dist: pytesseract
Requires-Dist: pyPDF2
Requires-Dist: pdf2image
Requires-Dist: beautifulsoup4>=4.9.0
Requires-Dist: Jinja2>=3.0.0
Requires-Dist: pymupdf
Requires-Dist: google-generativeai
Requires-Dist: tenacity
